careers/__init__.py
careers/api/__init__.py
careers/api/apps.py
careers/api/urls.py
careers/apps/__init__.py
careers/apps/categories/__init__.py
careers/apps/categories/apps.py
careers/apps/categories/migrations/0001_initial.py
careers/apps/categories/migrations/__init__.py
careers/apps/categories/models.py
careers/apps/categories/tests/__init__.py
careers/apps/categories/tests/test_models.py
careers/apps/home/__init__.py
careers/apps/home/apps.py
careers/apps/home/migrations/0001_initial.py
careers/apps/home/migrations/0002_create_homepage.py
careers/apps/home/migrations/__init__.py
careers/apps/home/models.py
careers/apps/home/tests/__init__.py
careers/apps/home/tests/test_models.py
careers/apps/indexes/__init__.py
careers/apps/indexes/apps.py
careers/apps/indexes/migrations/0001_initial.py
careers/apps/indexes/migrations/__init__.py
careers/apps/indexes/models.py
careers/apps/indexes/tests/__init__.py
careers/apps/indexes/tests/test_models.py
careers/apps/jobs/__init__.py
careers/apps/jobs/apps.py
careers/apps/jobs/migrations/0001_initial.py
careers/apps/jobs/migrations/0002_initial.py
careers/apps/jobs/migrations/0003_alter_job_details.py
careers/apps/jobs/migrations/__init__.py
careers/apps/jobs/models.py
careers/apps/jobs/tests/__init__.py
careers/apps/jobs/tests/test_models.py
careers/apps/mixins.py
careers/apps/signals.py
careers/apps/tags/__init__.py
careers/apps/tags/apps.py
careers/apps/tags/migrations/0001_initial.py
careers/apps/tags/migrations/__init__.py
careers/apps/tags/models.py
careers/apps.py
careers/cms/__init__.py
careers/cms/apps.py
careers/cms/blocks.py
careers/ui/__init__.py
careers/ui/apps.py
careers/ui/forms.py
careers/ui/locale/ar/LC_MESSAGES/django.po
careers/ui/locale/cn/LC_MESSAGES/django.po
careers/ui/locale/de/LC_MESSAGES/django.po
careers/ui/locale/es/LC_MESSAGES/django.po
careers/ui/locale/fr/LC_MESSAGES/django.po
careers/ui/locale/tr/LC_MESSAGES/django.po
careers/ui/mixins.py
careers/ui/static/careers/.prettierrc
django_w_careers-1.0.5.dist-info/METADATA
django_w_careers-1.0.5.dist-info/WHEEL
django_w_careers-1.0.5.dist-info/licenses/LICENSE
django_w_careers-1.0.5.dist-info/RECORD
