Metadata-Version: 2.4
Name: django-w-careers
Version: 1.0.5
Summary: A reusable, production-ready job posting application (One employer) built with Python, Django, Django REST Framework, and Wagtail CMS, styled with Tailwind CSS and daisyUI. It provides modern theming, optional APIs, and sensible defaults.
License: MIT
License-File: LICENSE
Author: Yousef Abu Shanab
Author-email: josephyousef249@gmail.com
Requires-Python: >=3.10
Classifier: License :: OSI Approved :: MIT License
Classifier: Programming Language :: Python :: 3
Classifier: Programming Language :: Python :: 3.10
Classifier: Programming Language :: Python :: 3.11
Classifier: Programming Language :: Python :: 3.12
Classifier: Programming Language :: Python :: 3.13
Classifier: Programming Language :: Python :: 3.14
Requires-Dist: django (>=5.2.1)
Requires-Dist: django-countries (>=7.6.1)
Requires-Dist: django-filter (>=25.1)
Requires-Dist: djangorestframework (>=3.16.0)
Requires-Dist: drf-restwind (>=0.2.0)
Requires-Dist: wagtail (>=7.0)
Requires-Dist: wagtail-tw-blocks (>=0.2.6)
Project-URL: Documentation, https://github.com/youzarsiph/django-w-careers
Project-URL: Homepage, https://github.com/youzarsiph/django-w-careers
Project-URL: Repository, https://github.com/youzarsiph/django-w-careers
